package_index.py
package_index-1.0.0b4.dist-info/LICENSE
package_index-1.0.0b4.dist-info/METADATA
package_index-1.0.0b4.dist-info/WHEEL
package_index-1.0.0b4.dist-info/top_level.txt
package_index-1.0.0b4.dist-info/RECORD
