Metadata-Version: 2.1
Name: package-index
Version: 1.0.0b4
Summary: Dataclasses API for PyPI and other warehouses.
Home-page: https://github.com/mdrachuk/package-index
Author: mdrachuk
Author-email: misha@drach.uk
License: MIT
Project-URL: Pipelines, https://dev.azure.com/misha-drachuk/package-index
Project-URL: Source, https://github.com/mdrachuk/package-index/
Project-URL: Issues, https://github.com/mdrachuk/package-index/issues
Keywords: python packaging pypi warehouse
Platform: UNKNOWN
Classifier: Intended Audience :: Developers
Classifier: Topic :: Utilities
Classifier: Development Status :: 3 - Alpha
Classifier: License :: OSI Approved :: MIT License
Classifier: Natural Language :: English
Classifier: Operating System :: MacOS :: MacOS X
Classifier: Operating System :: POSIX
Classifier: Operating System :: POSIX :: BSD
Classifier: Operating System :: POSIX :: Linux
Classifier: Operating System :: Microsoft :: Windows
Classifier: Programming Language :: Python
Classifier: Programming Language :: Python :: 3.7
Classifier: Programming Language :: Python :: Implementation :: CPython
Classifier: Typing :: Typed
Requires-Python: >=3.7
Requires-Dist: requests (>=2.22.0)
Requires-Dist: serious (==1.0.0.dev20)
